gvcss/__init__.py
gvcss/gvc_variant_pipeline.py
gvcss/pipeline.py
gvcss/ssinfo_interface.py
gvcss/test/__init__.py
gvcss/test/test.py
gvcss-1.0.2.data/scripts/gvcss_cli.py
gvcss-1.0.2.dist-info/METADATA
gvcss-1.0.2.dist-info/WHEEL
gvcss-1.0.2.dist-info/top_level.txt
gvcss-1.0.2.dist-info/RECORD
