Metadata-Version: 2.1
Name: gvcss
Version: 1.0.2
Summary: gvcss is single sample somatic mutations (SNV, InDel, SV) from FASTQ files.
Home-page: UNKNOWN
Author: bob zhang
Author-email: bob.zhang@genowis.com
License: UNKNOWN
Platform: UNKNOWN
Classifier: Programming Language :: Python :: 2.7
Classifier: License :: Free For Educational Use
Requires-Python: <3
Requires-Dist: toil (==3.19.0)
Requires-Dist: gvc4fastq
Requires-Dist: docker (==2.5.1)
Requires-Dist: toil-runner
